client/__init__.py
client/client_start.py
DBnPYQT_mess_client-0.0.1.dist-info/METADATA
DBnPYQT_mess_client-0.0.1.dist-info/WHEEL
DBnPYQT_mess_client-0.0.1.dist-info/top_level.txt
DBnPYQT_mess_client-0.0.1.dist-info/RECORD
