Metadata-Version: 2.1
Name: DBnPYQT-mess-client
Version: 0.0.1
Summary: DBnPYQT_mess_client
Home-page: UNKNOWN
Author: Aleksandr Sharov
Author-email: ssh7@bk.ru
License: UNKNOWN
Platform: UNKNOWN
Requires-Dist: PyQt5
Requires-Dist: sqlalchemy
Requires-Dist: pycryptodome
Requires-Dist: pycryptodomex
